colorizon/backgrounds.py
colorizon/colors.py
colorizon/formattings.py
colorizon-0.0.3.dist-info/LICENSE
colorizon-0.0.3.dist-info/METADATA
colorizon-0.0.3.dist-info/WHEEL
colorizon-0.0.3.dist-info/top_level.txt
colorizon-0.0.3.dist-info/RECORD
