Metadata-Version: 2.1
Name: colorizon
Version: 0.0.3
Summary: A small library to make it easy to use colors in Python
Home-page: https://github.com/FelipeSavazii/Colorizon
Author: Felipe Savazi
Author-email: dev@felipesavazi.com
License: MIT
Project-URL: Documentation, https://github.com/FelipeSavazii/Colorizon#documentation
Project-URL: Issue tracker, https://github.com/FelipeSavazii/Colorizon/issues
Platform: UNKNOWN
Classifier: Development Status :: 5 - Production/Stable
Classifier: License :: OSI Approved :: MIT License
Classifier: Intended Audience :: Developers
Classifier: Natural Language :: English
Classifier: Operating System :: OS Independent
Classifier: Programming Language :: Python :: 3.8
Classifier: Programming Language :: Python :: 3.9
Classifier: Programming Language :: Python :: 3.10
Requires-Python: >=3.8.0
License-File: LICENSE
